{
    "name": "gateway",
    "package": "com.fruit.gateway",
    "versionCode": "2.0.0",
    "versionNumber": 1,
    "ENV":"debug",
    "desc": "app deploy platform",
    "db": {
        "gateway": {
            "type": "mongodb",
            "content": {
                "host": "mxd99.vincent78.top",
                "port": 27017,
                "db_name": "appManager",
                "username": "appManager",
                "password": "moxi123",
                "useObjectId": true
            }
        }
    },
    "cache": {
        "gateway": {
            "type": "redis",
            "content": {
                "host": "mxd99.vincent78.top",
                "port": 6379,
                "auth": "moxi123",
                "select": 1
            }
        }
    },
    "kafka": {
        "consumer": {
            "bootstrap.servers": "mxd99.vincent78.top:9092,mxd99.vincent78.top:9093,mxd99.vincent78.top:9094",
            "group.id":"ip_lottery",
            "auto.offset.reset":"earliest"
        },
        "producer": {
            "bootstrap.servers": "mxd99.vincent78.top:9092,mxd99.vincent78.top:9093,mxd99.vincent78.top:9094",
            "acks":"0"
        }
    },
    "oss": {
        "endpoint":"oss-cn-shenzhen.aliyuncs.com",
        "accessKeyId":"LTAIaHvWJCsPbIC0",
        "accessKeySecret":"JwebiUEZsNvG6ZrdfvDTWmhKeXzfQZ",
        "bucket":"rngx"
    },
    "web":{
        "type":"https",
        "jks":"mx.keystore",
        "pwd":"moxi123",
        "path":"/gateway",
        "port": 8080,
        "allowedHeader": [
            "Access-Control-Request-Method",
            "Access-Control-Allow-Credentials",
            "Access-Control-Allow-Origin",
            "Access-Control-Allow-Headers",
            "X-PINGARUNER",
            "Content-Type",
            "clientId"
        ],
        "authentication": [
            "app",
            "cache",
            "filter",
            "upgrade",
            "user"
        ],
        "static": [
            {"path":"/css/*","target":"/css"},
            {"path":"/img/*","target":"/img"},
            {"path":"/js/*","target":"/js"}
        ]
    },
    "uploadRootPath":"file-uploads",
    "cluster": {
        "type": "zookeeper",
        "FromCluster": false,
        "conf": {
            "zookeeperHosts": "mxd99.vincent78.top:2181",
            "sessionTimeout": 20000,
            "connectTimeout": 3000,
            "rootPath": "io.vertx",
            "confPath": "/io.vertx/vx.api.gateway/conf",
            "retry": {
                "initialSleepTime": 100,
                "intervalTimes": 10000,
                "maxTimes": 5
            }
        }
    },
    "vertxOptions": {
    }
}